imitater/__init__.py
imitater/agent/__init__.py
imitater/agent/aligned.py
imitater/agent/function.py
imitater/agent/react.py
imitater/agent/registry.py
imitater/agent/types.py
imitater/model/__init__.py
imitater/model/chat_model.py
imitater/model/embed_model.py
imitater/service/__init__.py
imitater/service/app.py
imitater/service/chat.py
imitater/service/common.py
imitater/service/embed.py
imitater/service/protocol.py
imitater/utils/__init__.py
imitater/utils/generic.py
imitater/utils/modelscope.py
imitater-0.2.4.dist-info/LICENSE
imitater-0.2.4.dist-info/METADATA
imitater-0.2.4.dist-info/WHEEL
imitater-0.2.4.dist-info/entry_points.txt
imitater-0.2.4.dist-info/top_level.txt
imitater-0.2.4.dist-info/RECORD
