Metadata-Version: 2.1
Name: imitater
Version: 0.2.4
Home-page: https://github.com/the-seeds/imitater
Author: the-seeds
License: Apache 2.0 License
Keywords: LLM
Classifier: Development Status :: 4 - Beta
Classifier: Intended Audience :: Developers
Classifier: Intended Audience :: Education
Classifier: Intended Audience :: Science/Research
Classifier: License :: OSI Approved :: Apache Software License
Classifier: Operating System :: OS Independent
Classifier: Programming Language :: Python :: 3
Classifier: Programming Language :: Python :: 3.9
Classifier: Programming Language :: Python :: 3.10
Classifier: Programming Language :: Python :: 3.11
Classifier: Topic :: Scientific/Engineering :: Artificial Intelligence
Requires-Python: >=3.9.0
License-File: LICENSE
Requires-Dist: vllm ==0.4.3
Requires-Dist: infinity-emb[optimum,torch] ==0.0.40
Requires-Dist: openai >=1.5.0
Requires-Dist: uvicorn
Requires-Dist: pydantic
Requires-Dist: fastapi
Requires-Dist: sse-starlette
